deeptminter/__init__.py
deeptminter/load.py
deeptminter/predict.py
deeptminter/util/AAProperty.py
deeptminter/util/AARepresentation.py
deeptminter/util/Conservation.py
deeptminter/util/Console.py
deeptminter/util/Cumulative.py
deeptminter/util/DataInitializer.py
deeptminter/util/EvolutionaryProfile.py
deeptminter/util/FSPosition.py
deeptminter/util/FSingle.py
deeptminter/util/Fasta.py
deeptminter/util/Feature.py
deeptminter/util/InformationTheory.py
deeptminter/util/Length.py
deeptminter/util/MSA.py
deeptminter/util/Phobius.py
deeptminter/util/Position.py
deeptminter/util/Reader.py
deeptminter/util/SSFasta.py
deeptminter/util/SSingle.py
deeptminter/util/Sequence.py
deeptminter/util/Stacking.py
deeptminter/util/Tinker.py
deeptminter/util/WSingle.py
deeptminter/util/__init__.py
deeptminter/util/gdca.julia
deeptminter/util/troll.sh
deeptminter-0.0.1.dist-info/LICENSE
deeptminter-0.0.1.dist-info/METADATA
deeptminter-0.0.1.dist-info/WHEEL
deeptminter-0.0.1.dist-info/entry_points.txt
deeptminter-0.0.1.dist-info/RECORD
