Metadata-Version: 2.3
Name: deeptminter
Version: 0.0.1
Summary: 
Author: Jianfeng Sun
Author-email: jianfeng.sunmt@gmail.com
Requires-Python: >=3.11,<4
Classifier: Programming Language :: Python :: 3
Classifier: Programming Language :: Python :: 3.11
Classifier: Programming Language :: Python :: 3.12
Classifier: Programming Language :: Python :: 3.13
Requires-Dist: biopython (>=1.85,<2.0)
Requires-Dist: click (>=8.1.8,<9.0.0)
Requires-Dist: joblib (==1.4.2)
Requires-Dist: numpy (==2.1.3)
Requires-Dist: pandas (==2.2.3)
Requires-Dist: pyfiglet (>=1.0.2,<2.0.0)
Requires-Dist: scikit-learn (>=1.6.1,<2.0.0)
Requires-Dist: tensorflow (==2.19)
